xfaster/__init__.py
xfaster/batch_tools.py
xfaster/gcorr_tools.py
xfaster/parse_tools.py
xfaster/spec_tools.py
xfaster/xfaster_class.py
xfaster/xfaster_exec.py
xfaster-1.2.0.dist-info/LICENSE
xfaster-1.2.0.dist-info/METADATA
xfaster-1.2.0.dist-info/WHEEL
xfaster-1.2.0.dist-info/entry_points.txt
xfaster-1.2.0.dist-info/top_level.txt
xfaster-1.2.0.dist-info/RECORD
