Metadata-Version: 2.1
Name: xfaster
Version: 1.2.0
Summary: A fast power spectrum and likelihood estimator for CMB datasets
Home-page: https://github.com/SPIDERCMB/xfaster
License: MIT
Requires-Python: >=3.0
License-File: LICENSE
Requires-Dist: numpy >1.17.5
Requires-Dist: healpy
Requires-Dist: camb
Requires-Dist: emcee
Requires-Dist: h5py
